[{"country":"mnQzjZDkTes=","highlevel":"h6yAfBrnD2M=","birthdate":"\/i5FURSpvOE=","address":"0ZClCPdC1B4=","city":"mnQzjZDkTes=","user_name":"8d\/jr8kEJ\/s=","total_gametime":"ykEvTqkTXR8l\/Msztq4pKXkF+YsF0PGD","diagnosis":"G2PSHSnmIE8MiQUxBOJ\/bA==","state":"mnQzjZDkTes=","interaction_array":["fuC8X15AMHY=","Xjej1rQoBsU=","zYZsKBsLlZY=","cgtHiAR\/R4A=","i7eCxJkzMB4=","aYRIIs4YnUY=","3qxl04ptK34=","CmT9YXzySnU=","fIr0jLWxcmc=","23YhSUQBwzY=","0qs0Ps1F7UE=","3xXRlUXwwK8=","P5Ybar6U7b4=","3Slsg1Cy8Uc=","N03jtt820+Q=","KHcUWA6a9LQ=","hezQD618arg=","eAdiFwfwtSY=","tVkEAARUIjc=","JcVlp1Vogq0=","3yei+NVREn4=","cNjOW\/bbN\/k=","jxs0DReLlTM=","TDZtt4H\/2zk=","Mv0fhUS1gTg=","Mv0fhUS1gTg=","jMLCpRRAozQ=","Mv0fhUS1gTg=","jMLCpRRAozQ=","Mv0fhUS1gTg=","jMLCpRRAozQ=","fuC8X15AMHY=","jMLCpRRAozQ=","sxxCUfM4UDU=","jMLCpRRAozQ=","fuC8X15AMHY=","jMLCpRRAozQ=","fuC8X15AMHY=","jMLCpRRAozQ=","fuC8X15AMHY=","jMLCpRRAozQ=","6PiK3uq18lE=","jMLCpRRAozQ=","6PiK3uq18lE=","jMLCpRRAozQ=","cgtHiAR\/R4A=","Mv0fhUS1gTg=","Mv0fhUS1gTg=","Mv0fhUS1gTg=","Mv0fhUS1gTg=","Mv0fhUS1gTg=","Mv0fhUS1gTg=","Mv0fhUS1gTg=","Mv0fhUS1gTg=","Mv0fhUS1gTg=","jMLCpRRAozQ=","cgtHiAR\/R4A=","Mv0fhUS1gTg=","Mv0fhUS1gTg=","Mv0fhUS1gTg=","Mv0fhUS1gTg=","Mv0fhUS1gTg=","Mv0fhUS1gTg=","Mv0fhUS1gTg=","Mv0fhUS1gTg=","Mv0fhUS1gTg=","jMLCpRRAozQ=","3+9GiKGLeAg=","jMLCpRRAozQ=","3+9GiKGLeAg=","jMLCpRRAozQ=","fuC8X15AMHY=","jMLCpRRAozQ=","fuC8X15AMHY=","G1VekQq9slQ=","RGafxuxI50Y=","cgtHiAR\/R4A=","+xg7QmS8Nw4=","EWO76XX2egg=","3qxl04ptK34=","0B1Fo2w\/ANY=","Lb15UpEckqc=","23YhSUQBwzY=","qb0zuA9QBvI=","ujGS53CGYT0=","P5Ybar6U7b4=","5QSJZNw1lJk=","WyEo6YBd5zU=","KHcUWA6a9LQ=","nUcxiRC7iuU=","IwFE4pHENA0=","tVkEAARUIjc=","Fsj8qNInuvY=","JxgkA7QFp1A=","cNjOW\/bbN\/k=","90HdJPtW65k=","id8ZgjO\/sB0=","Mv0fhUS1gTg=","Mv0fhUS1gTg=","jMLCpRRAozQ=","fuC8X15AMHY=","jMLCpRRAozQ=","fuC8X15AMHY=","jMLCpRRAozQ=","fuC8X15AMHY=","jMLCpRRAozQ=","sxxCUfM4UDU=","jMLCpRRAozQ=","fuC8X15AMHY=","jMLCpRRAozQ=","fuC8X15AMHY=","jMLCpRRAozQ=","fuC8X15AMHY=","jMLCpRRAozQ=","P5Ybar6U7b4=","KHcUWA6a9LQ=","Mv0fhUS1gTg=","Mv0fhUS1gTg=","Mv0fhUS1gTg=","Mv0fhUS1gTg=","Mv0fhUS1gTg=","Mv0fhUS1gTg=","Mv0fhUS1gTg=","Mv0fhUS1gTg=","jMLCpRRAozQ=","P5Ybar6U7b4=","KHcUWA6a9LQ=","Mv0fhUS1gTg=","Mv0fhUS1gTg=","Mv0fhUS1gTg=","Mv0fhUS1gTg=","Mv0fhUS1gTg=","Mv0fhUS1gTg=","Mv0fhUS1gTg=","Mv0fhUS1gTg=","jMLCpRRAozQ=","+sAOadX8lu4=","jMLCpRRAozQ=","Ah0g+ztIkRA=","jMLCpRRAozQ=","fuC8X15AMHY=","jMLCpRRAozQ=","fuC8X15AMHY=","j9QQYF4CaTY=","KpjI3h1P6zU=","cgtHiAR\/R4A=","5QSJZNw1lJk=","mLd+WZZ5bqo=","3qxl04ptK34=","RezxiWE\/5xo=","02dx1\/vr9F4=","23YhSUQBwzY=","uE6SvIUTgWk=","8ud+M1a9afE=","P5Ybar6U7b4=","O6eNO6zDlcw=","RgtvOtsYcS8=","KHcUWA6a9LQ=","JgE8zC1wNbY=","2TrIFB+PWEg=","tVkEAARUIjc=","lss0HEsvKwY=","frjlLH+2qmA=","cNjOW\/bbN\/k=","obcC0Cwil3g=","IHZmqZmE2pI=","Mv0fhUS1gTg=","Mv0fhUS1gTg=","jMLCpRRAozQ=","cgtHiAR\/R4A=","jMLCpRRAozQ=","cgtHiAR\/R4A=","jMLCpRRAozQ=","fuC8X15AMHY=","jMLCpRRAozQ=","sxxCUfM4UDU=","jMLCpRRAozQ=","fuC8X15AMHY=","jMLCpRRAozQ=","fuC8X15AMHY=","jMLCpRRAozQ=","fuC8X15AMHY=","jMLCpRRAozQ=","Mv0fhUS1gTg=","Mv0fhUS1gTg=","Mv0fhUS1gTg=","Mv0fhUS1gTg=","Mv0fhUS1gTg=","Mv0fhUS1gTg=","Mv0fhUS1gTg=","Mv0fhUS1gTg=","Mv0fhUS1gTg=","Mv0fhUS1gTg=","jMLCpRRAozQ=","cNjOW\/bbN\/k=","cNjOW\/bbN\/k=","Mv0fhUS1gTg=","Mv0fhUS1gTg=","Mv0fhUS1gTg=","Mv0fhUS1gTg=","Mv0fhUS1gTg=","Mv0fhUS1gTg=","Mv0fhUS1gTg=","Mv0fhUS1gTg=","jMLCpRRAozQ=","cgtHiAR\/R4A=","jMLCpRRAozQ=","WcDLStgp\/CE=","jMLCpRRAozQ=","DCv0GPm6hlk=","jMLCpRRAozQ=","fuC8X15AMHY=","uO+enRpleXU=","Adp\/W7r+vxY=","cgtHiAR\/R4A=","Aimq5asvs\/E=","tBn60IXMoEY=","3qxl04ptK34=","X\/caXDRs7EI=","ZPnCdP\/TR\/E=","23YhSUQBwzY=","lVa1NAgTndE=","kLSYlXM64fM=","P5Ybar6U7b4=","JgE8zC1wNbY=","i1i7dZTQyw0=","KHcUWA6a9LQ=","dqoZ7ZN3uWg=","GmNr4BiCHnQ=","tVkEAARUIjc=","uO+enRpleXU=","3eXClvZejmI=","cNjOW\/bbN\/k=","dBSwoo3w\/FQ=","hzvgltWyst0=","Mv0fhUS1gTg=","Mv0fhUS1gTg=","jMLCpRRAozQ=","cgtHiAR\/R4A=","jMLCpRRAozQ=","cgtHiAR\/R4A=","jMLCpRRAozQ=","Mv0fhUS1gTg=","jMLCpRRAozQ=","sxxCUfM4UDU=","jMLCpRRAozQ=","fuC8X15AMHY=","jMLCpRRAozQ=","fuC8X15AMHY=","jMLCpRRAozQ=","fuC8X15AMHY=","jMLCpRRAozQ=","3qxl04ptK34=","3qxl04ptK34=","3qxl04ptK34=","Mv0fhUS1gTg=","Mv0fhUS1gTg=","Mv0fhUS1gTg=","Mv0fhUS1gTg=","Mv0fhUS1gTg=","Mv0fhUS1gTg=","Mv0fhUS1gTg=","jMLCpRRAozQ=","3qxl04ptK34=","3qxl04ptK34=","3qxl04ptK34=","Mv0fhUS1gTg=","Mv0fhUS1gTg=","Mv0fhUS1gTg=","Mv0fhUS1gTg=","Mv0fhUS1gTg=","Mv0fhUS1gTg=","Mv0fhUS1gTg=","jMLCpRRAozQ=","e\/wuxbOOpIw=","jMLCpRRAozQ=","DLkCN0P185M=","jMLCpRRAozQ=","fuC8X15AMHY=","jMLCpRRAozQ=","fuC8X15AMHY=","KQiyzjJU8J0=","VrjHVHLwBPE=","cgtHiAR\/R4A=","jwZnY2UIYlc=","qt+qTLXnb54=","3qxl04ptK34=","Wwqxdw5TeQY=","zTkIHf7Cle8=","23YhSUQBwzY=","MKQk5fMOLoI=","vTdx5+Cy+Vo=","P5Ybar6U7b4=","rF2NXm7jrYg=","EWAgRambuJk=","KHcUWA6a9LQ=","\/09SFNB+RJI=","rsUWUueYWxY=","tVkEAARUIjc=","owFPiBfgymQ=","qXuYte9D4aQ=","cNjOW\/bbN\/k=","4tsVtlHmd9s=","iVTRk0Xcy10=","Mv0fhUS1gTg=","Mv0fhUS1gTg=","jMLCpRRAozQ=","3qxl04ptK34=","jMLCpRRAozQ=","3qxl04ptK34=","jMLCpRRAozQ=","Mv0fhUS1gTg=","jMLCpRRAozQ=","sxxCUfM4UDU=","jMLCpRRAozQ=","fuC8X15AMHY=","jMLCpRRAozQ=","fuC8X15AMHY=","jMLCpRRAozQ=","fuC8X15AMHY=","jMLCpRRAozQ=","3qxl04ptK34=","P5Ybar6U7b4=","KHcUWA6a9LQ=","cgtHiAR\/R4A=","Mv0fhUS1gTg=","Mv0fhUS1gTg=","Mv0fhUS1gTg=","Mv0fhUS1gTg=","Mv0fhUS1gTg=","Mv0fhUS1gTg=","jMLCpRRAozQ=","3qxl04ptK34=","cgtHiAR\/R4A=","P5Ybar6U7b4=","KHcUWA6a9LQ=","Mv0fhUS1gTg=","Mv0fhUS1gTg=","Mv0fhUS1gTg=","Mv0fhUS1gTg=","Mv0fhUS1gTg=","Mv0fhUS1gTg=","jMLCpRRAozQ=","cgtHiAR\/R4A=","jMLCpRRAozQ=","GQgLRVe1BfQ=","jMLCpRRAozQ=","ykEvTqkTXR8l\/Msztq4pKXkF+YsF0PGD","jMLCpRRAozQ="],"key":"RizaonwIQL8=","zip_code":"mnQzjZDkTes="},{"country":"baTLOo4l0jQ=","highlevel":"QrAQrOWB0+s=","birthdate":"baTLOo4l0jQ=","address":"baTLOo4l0jQ=","city":"baTLOo4l0jQ=","user_name":"baTLOo4l0jQ=","total_gametime":"Njt1UDTQNeU=","diagnosis":"CSlZSPGajLgVYt0EI\/iseA==","state":"baTLOo4l0jQ=","interaction_array":["Rrj7YrISuUo=","J21nSSymPLA=","4P52d\/NcDV8=","fTELrnP69Eo=","CV7R\/YYpUf4=","39ImDZaHfxA=","URjzvPeUn2I=","F2Vi+Saa9jU=","2\/PRkDNFruE=","URHZOTyuOXU=","FwKpqgkgrdY=","Yz9S1SUKiyc=","X+7RsqVzRyU=","19G1UtdEgBs=","EdxmqQX32+k=","AIrMp3SLFwE=","sRivol5kObg=","9U+dYv+p05E=","dGFRs7Vd6qQ=","EyV9uFn96fY=","4dLfjJ9A00o=","oJbXbP0Z6Wk=","FmyMMI0qgq8=","4BChDIWl1QY=","4ctGsplGyG8=","4ctGsplGyG8=","20nhkhwI\/rg=","4ctGsplGyG8=","20nhkhwI\/rg=","4ctGsplGyG8=","20nhkhwI\/rg=","Rrj7YrISuUo=","20nhkhwI\/rg=","90tDo9ANatY=","20nhkhwI\/rg=","Rrj7YrISuUo=","20nhkhwI\/rg=","Rrj7YrISuUo=","20nhkhwI\/rg=","Rrj7YrISuUo=","20nhkhwI\/rg=","qcE9ngXzd8M=","20nhkhwI\/rg=","qcE9ngXzd8M=","20nhkhwI\/rg=","X+7RsqVzRyU=","4ctGsplGyG8=","4ctGsplGyG8=","4ctGsplGyG8=","4ctGsplGyG8=","4ctGsplGyG8=","4ctGsplGyG8=","4ctGsplGyG8=","4ctGsplGyG8=","4ctGsplGyG8=","20nhkhwI\/rg=","X+7RsqVzRyU=","4ctGsplGyG8=","4ctGsplGyG8=","4ctGsplGyG8=","4ctGsplGyG8=","4ctGsplGyG8=","4ctGsplGyG8=","4ctGsplGyG8=","4ctGsplGyG8=","4ctGsplGyG8=","20nhkhwI\/rg=","Zu9fIeoccbA=","20nhkhwI\/rg=","Zu9fIeoccbA=","20nhkhwI\/rg=","Rrj7YrISuUo=","20nhkhwI\/rg=","Rrj7YrISuUo=","VX\/u8WTkw7M=","e0WMq\/2eKiE=","fTELrnP69Eo=","e5rATHKHoJk=","iGA2kG\/ZpMI=","URjzvPeUn2I=","Kwqars9Wl+s=","P+B86P0dhzM=","URHZOTyuOXU=","19G1UtdEgBs=","JiQ8uXQ8Htw=","X+7RsqVzRyU=","LuPXYOwHN9U=","S6puomAj43k=","AIrMp3SLFwE=","o8ZsfcTUJVA=","UzsGt7b22OU=","dGFRs7Vd6qQ=","IohvGdRy5t0=","iS6nNVg+ZQA=","oJbXbP0Z6Wk=","WiH1IdMNAF0=","rcAQs8SS5VI=","4ctGsplGyG8=","4ctGsplGyG8=","20nhkhwI\/rg=","Rrj7YrISuUo=","20nhkhwI\/rg=","Rrj7YrISuUo=","20nhkhwI\/rg=","Rrj7YrISuUo=","20nhkhwI\/rg=","90tDo9ANatY=","20nhkhwI\/rg=","Rrj7YrISuUo=","20nhkhwI\/rg=","Rrj7YrISuUo=","20nhkhwI\/rg=","Rrj7YrISuUo=","20nhkhwI\/rg=","dGFRs7Vd6qQ=","oJbXbP0Z6Wk=","4ctGsplGyG8=","4ctGsplGyG8=","4ctGsplGyG8=","4ctGsplGyG8=","4ctGsplGyG8=","4ctGsplGyG8=","4ctGsplGyG8=","4ctGsplGyG8=","20nhkhwI\/rg=","dGFRs7Vd6qQ=","oJbXbP0Z6Wk=","4ctGsplGyG8=","4ctGsplGyG8=","4ctGsplGyG8=","4ctGsplGyG8=","4ctGsplGyG8=","4ctGsplGyG8=","4ctGsplGyG8=","4ctGsplGyG8=","20nhkhwI\/rg=","IX8Ngtk3W2A=","20nhkhwI\/rg=","wkWDv8LPBRw=","20nhkhwI\/rg=","Rrj7YrISuUo=","20nhkhwI\/rg=","Rrj7YrISuUo=","dWqnsS7HpxQ=","T6Aegf+\/GQI=","fTELrnP69Eo=","69HNbUztNM4=","JlPpp3SMfow=","URjzvPeUn2I=","oyvJskKbrsA=","IIXCRBLi4Rc=","URHZOTyuOXU=","w7erlftJ5jA=","TOR+iAk5Njg=","X+7RsqVzRyU=","D5dDXowQw0I=","5nYH2REi3Jw=","AIrMp3SLFwE=","h1S4OHyvJYk=","B9i+9OWG+Lw=","dGFRs7Vd6qQ=","32m6PKqMpqY=","gYJYnloBGCc=","oJbXbP0Z6Wk=","KRhCcPqmiRo=","3iJ5MypNZRI=","4ctGsplGyG8=","4ctGsplGyG8=","20nhkhwI\/rg=","fTELrnP69Eo=","20nhkhwI\/rg=","fTELrnP69Eo=","20nhkhwI\/rg=","Rrj7YrISuUo=","20nhkhwI\/rg=","90tDo9ANatY=","20nhkhwI\/rg=","Rrj7YrISuUo=","20nhkhwI\/rg=","Rrj7YrISuUo=","20nhkhwI\/rg=","Rrj7YrISuUo=","20nhkhwI\/rg=","URHZOTyuOXU=","Rrj7YrISuUo=","X+7RsqVzRyU=","4ctGsplGyG8=","4ctGsplGyG8=","4ctGsplGyG8=","4ctGsplGyG8=","4ctGsplGyG8=","4ctGsplGyG8=","4ctGsplGyG8=","20nhkhwI\/rg=","URHZOTyuOXU=","Rrj7YrISuUo=","X+7RsqVzRyU=","4ctGsplGyG8=","4ctGsplGyG8=","4ctGsplGyG8=","4ctGsplGyG8=","4ctGsplGyG8=","4ctGsplGyG8=","4ctGsplGyG8=","20nhkhwI\/rg=","nOdqBfQJzGA=","20nhkhwI\/rg=","cIM+wRr+k\/A=","20nhkhwI\/rg=","Rrj7YrISuUo=","20nhkhwI\/rg=","Rrj7YrISuUo=","hLxRwQDTUdg=","kF0al3+cCLg=","fTELrnP69Eo=","LAZ\/dudwiBk=","2fHF+BqCUFo=","URjzvPeUn2I=","QLdZzXXOqJA=","SZ+Ek5UGvn0=","URHZOTyuOXU=","cr27ZTHFPFI=","CdzE1Bx35\/8=","X+7RsqVzRyU=","\/ckmtU2im4Y=","2wWHtmnsCic=","AIrMp3SLFwE=","6MgSiWRA\/0U=","8eC9\/SIy1aw=","dGFRs7Vd6qQ=","Hf255dbyfXA=","XvAH0k+1TBM=","oJbXbP0Z6Wk=","z6+5VAqqzHo=","VBaLbpqIxbc=","4ctGsplGyG8=","4ctGsplGyG8=","20nhkhwI\/rg=","URjzvPeUn2I=","20nhkhwI\/rg=","URjzvPeUn2I=","20nhkhwI\/rg=","Rrj7YrISuUo=","20nhkhwI\/rg=","90tDo9ANatY=","20nhkhwI\/rg=","Rrj7YrISuUo=","20nhkhwI\/rg=","Rrj7YrISuUo=","20nhkhwI\/rg=","Rrj7YrISuUo=","20nhkhwI\/rg=","oJbXbP0Z6Wk=","fTELrnP69Eo=","AIrMp3SLFwE=","4ctGsplGyG8=","4ctGsplGyG8=","4ctGsplGyG8=","4ctGsplGyG8=","4ctGsplGyG8=","4ctGsplGyG8=","4ctGsplGyG8=","20nhkhwI\/rg=","oJbXbP0Z6Wk=","fTELrnP69Eo=","AIrMp3SLFwE=","Rrj7YrISuUo=","4ctGsplGyG8=","4ctGsplGyG8=","4ctGsplGyG8=","4ctGsplGyG8=","4ctGsplGyG8=","4ctGsplGyG8=","20nhkhwI\/rg=","fTELrnP69Eo=","20nhkhwI\/rg=","RVYc30C0gpw=","20nhkhwI\/rg=","fuRWx9m4dl9MGXfh3cWW5Ah6Igz\/4gMK","20nhkhwI\/rg=","Rrj7YrISuUo=","2N5H20LTQiE=","l4W4B55ogIM=","fTELrnP69Eo=","21+oQCcJIZ8=","6et4aN\/ngkw=","URjzvPeUn2I=","rHH0sThYN6c=","aSV7dj9Okbk=","URHZOTyuOXU=","IL1s9zanpUs=","G+xtPBoWN90=","X+7RsqVzRyU=","fKFPdjFYjow=","XQyXSnXXtoU=","AIrMp3SLFwE=","ARpZfiJhrdg=","IIXCRBLi4Rc=","dGFRs7Vd6qQ=","BcJ+YyCF82w=","SpeLxwjsinY=","oJbXbP0Z6Wk=","WW0bdstDz2w=","5Y0vVMznjt8=","4ctGsplGyG8=","4ctGsplGyG8=","20nhkhwI\/rg=","URjzvPeUn2I=","20nhkhwI\/rg=","URjzvPeUn2I=","20nhkhwI\/rg=","4ctGsplGyG8=","20nhkhwI\/rg=","90tDo9ANatY=","20nhkhwI\/rg=","Rrj7YrISuUo=","20nhkhwI\/rg=","Rrj7YrISuUo=","20nhkhwI\/rg=","Rrj7YrISuUo=","20nhkhwI\/rg=","4ctGsplGyG8=","4ctGsplGyG8=","4ctGsplGyG8=","4ctGsplGyG8=","4ctGsplGyG8=","4ctGsplGyG8=","4ctGsplGyG8=","4ctGsplGyG8=","4ctGsplGyG8=","4ctGsplGyG8=","20nhkhwI\/rg=","Rrj7YrISuUo=","Rrj7YrISuUo=","X+7RsqVzRyU=","X+7RsqVzRyU=","4ctGsplGyG8=","4ctGsplGyG8=","4ctGsplGyG8=","4ctGsplGyG8=","4ctGsplGyG8=","4ctGsplGyG8=","20nhkhwI\/rg=","fTELrnP69Eo=","20nhkhwI\/rg=","dsq2sFwdKmk=","20nhkhwI\/rg=","Njt1UDTQNeU=","20nhkhwI\/rg="],"key":"qD0anv0Z5io=","zip_code":"baTLOo4l0jQ="}]